{
  "displayName": "DHL Tracking Tools",
  "name": "util-functions-dhl",
  "platform": "web",
  "version": "1.0.46",
  "description": "DHL Utils provide a variety of useful events, conditions and actions for our click and event driven tracking approach.",
  "iconPath": "./src/resources/icon/dhl.svg",
  "author": {
    "name": "DHL CSI",
    "url": "https://github.com/fooku18/launch-dhl-utils-extension"
  },
  "viewBasePath": "src/view/",
  "actions": [
    {
      "displayName": "Direct Call",
      "name": "direct-call",
      "schema": {
        "$schema": "http://json-schema.org/draft-04/schema#",
        "type": "object",
        "properties": {
          "dc": {
            "type": "string",
            "pattern": "[\\w\\d]+"
          }
        }
      },
      "libPath": "src/lib/actions/directCall.js",
      "viewPath": "actions/directCall.html"
    },
    {
      "displayName": "Trigger Custom Event",
      "name": "trigger-custom-event",
      "schema": {
        "$schema": "http://json-schema.org/draft-04/schema#",
        "type": "object",
        "properties": {}
      },
      "libPath": "src/lib/actions/triggerCustomEvent.js",
      "viewPath": "actions/triggerCustomEvent.html"
    },
    {
      "displayName": "Set DataElement",
      "name": "set-dataelement",
      "schema": {
        "$schema": "http://json-schema.org/draft-04/schema#",
        "type": "object",
        "properties": {}
      },
      "libPath": "src/lib/actions/setDataelement.js",
      "viewPath": "actions/setDataelement.html"
    }
  ],
  "events": [
  ],
  "conditions": [
  ],
  "sharedModules": [
  ],
  "dataElements": [
    {
      "displayName": "Previous Value",
      "name": "previous-value",
      "schema": {
        "$schema": "http://json-schema.org/draft-04/schema#",
        "type": "object",
        "properties": {
          "name": {
            "type": "string",
            "minLength": 1
          },
          "details": {
            "type": "string",
            "minLength": 1
          }
        }
      },
      "libPath": "src/lib/dataElements/previousValue.js",
      "viewPath": "dataElements/previousValue.html"
    },
    {
      "displayName": "Previous Page Seconds Spent",
      "name": "previous-page-seconds-spent",
      "schema": {
        "$schema": "http://json-schema.org/draft-04/schema#",
        "type": "object",
        "properties": {}
      },
      "libPath": "src/lib/dataElements/previousPageSecondsSpent.js"
    },
    {
      "displayName": "Client Time",
      "name": "client-time",
      "schema": {
        "$schema": "http://json-schema.org/draft-04/schema#",
        "type": "object",
        "properties": {}
      },
      "libPath": "src/lib/dataElements/clientTime.js"
    },
    {
      "displayName": "Client Day",
      "name": "client-day",
      "schema": {
        "$schema": "http://json-schema.org/draft-04/schema#",
        "type": "object",
        "properties": {}
      },
      "libPath": "src/lib/dataElements/clientDay.js"
    },
    {
      "displayName": "Client Day Type",
      "name": "client-day-type",
      "schema": {
        "$schema": "http://json-schema.org/draft-04/schema#",
        "type": "object",
        "properties": {}
      },
      "libPath": "src/lib/dataElements/clientDayType.js"
    },
    {
      "displayName": "Page Load Time",
      "name": "page-load-time",
      "schema": {
        "$schema": "http://json-schema.org/draft-04/schema#",
        "type": "object",
        "properties": {}
      },
      "libPath": "src/lib/dataElements/pageLoadTime.js"
    },
    {
      "displayName": "Seconds Since Pageload",
      "name": "seconds-since-pageload",
      "schema": {
        "$schema": "http://json-schema.org/draft-04/schema#",
        "type": "object",
        "properties": {}
      },
      "libPath": "src/lib/dataElements/secondsSincePageload.js"
    },
    {
      "displayName": "Previous Page Percentage Viewed",
      "name": "previous-page-percentage-viewed",
      "schema": {
        "$schema": "http://json-schema.org/draft-04/schema#",
        "type": "object",
        "properties": {}
      },
      "libPath": "src/lib/dataElements/previousPagePercentageViewed.js",
      "viewPath": "dataElements/previousPagePercentageViewed.html"
    },
    {
      "displayName": "URL Pieces",
      "name": "url-pieces",
      "schema": {
        "$schema": "http://json-schema.org/draft-04/schema#",
        "type": "object",
        "properties": {}
      },
      "libPath": "src/lib/dataElements/urlPieces.js",
      "viewPath": "dataElements/urlPieces.html"
    },
    {
      "displayName": "Traffic Type",
      "name": "traffic-type",
      "schema": {
        "$schema": "http://json-schema.org/draft-04/schema#",
        "type": "object",
        "properties": {}
      },
      "libPath": "src/lib/dataElements/trafficType.js"
    }
  ]
}
